file_json/__about__.py
file_json/__init__.py
file_json/base.py
file_json/time_base_list.py
file_json/utils.py
file_json-0.1.0.dist-info/METADATA
file_json-0.1.0.dist-info/WHEEL
file_json-0.1.0.dist-info/licenses/LICENSE
file_json-0.1.0.dist-info/RECORD
